README.md
setup.py
asyncpg_migrate/__init__.py
asyncpg_migrate/constants.py
asyncpg_migrate/exceptions.py
asyncpg_migrate/loader.py
asyncpg_migrate/main.py
asyncpg_migrate/model.py
asyncpg_migrate.egg-info/PKG-INFO
asyncpg_migrate.egg-info/SOURCES.txt
asyncpg_migrate.egg-info/dependency_links.txt
asyncpg_migrate.egg-info/entry_points.txt
asyncpg_migrate.egg-info/requires.txt
asyncpg_migrate.egg-info/top_level.txt
asyncpg_migrate/engine/__init__.py
asyncpg_migrate/engine/downgrade.py
asyncpg_migrate/engine/migration.py
asyncpg_migrate/engine/upgrade.py