Metadata-Version: 2.1
Name: asyncpg-migrate
Version: 0.0.6
Summary: Dependabot Status](https://api.dependabot.com/badges/status?host=github&repo=kornicameister/asyncpg-migrate)](https://dependabot.com)
Home-page: https://github.com/kornicameister/asyncpg-migrate
Author: Tomasz Trębski
Author-email: kornicameister@gmail.com
License: Apache 2.0
Platform: UNKNOWN
Classifier: Development Status :: 2 - Pre-Alpha
Classifier: Environment :: Console
Classifier: Intended Audience :: Developers
Classifier: Intended Audience :: System Administrators
Classifier: License :: OSI Approved :: Apache Software License
Classifier: Operating System :: POSIX
Classifier: Operating System :: Unix
Classifier: Programming Language :: Python :: 3
Classifier: Programming Language :: Python :: 3.6
Classifier: Programming Language :: Python :: 3.7
Classifier: Programming Language :: Python :: 3.8
Classifier: Programming Language :: Python :: Implementation :: CPython
Classifier: Typing :: Typed
Requires-Python: >=3.6.0
Provides-Extra: uvloop
